mpv.cp39-win_amd64.pyd
pympv-0.9.0.data/data/Scripts/mpv.dll
pympv-0.9.0.data/data/include/client.h
pympv-0.9.0.data/data/include/opengl_cb.h
pympv-0.9.0.data/data/include/render.h
pympv-0.9.0.data/data/include/render_gl.h
pympv-0.9.0.data/data/include/stream_cb.h
pympv-0.9.0.data/data/libs/mpv.lib
pympv-0.9.0.dist-info/LICENSE
pympv-0.9.0.dist-info/METADATA
pympv-0.9.0.dist-info/WHEEL
pympv-0.9.0.dist-info/top_level.txt
pympv-0.9.0.dist-info/RECORD
