Metadata-Version: 2.1
Name: pympv
Version: 0.9.0
Summary: Python bindings for the libmpv library
Home-page: https://github.com/marcan/pympv
Author: Andre D
Author-email: andre@andred.ca
Maintainer: Hector Martin
Maintainer-email: marcan@marcan.st
License: UNKNOWN
Platform: UNKNOWN
Classifier: Development Status :: 3 - Alpha
Classifier: Programming Language :: Cython
Classifier: Topic :: Multimedia :: Sound/Audio :: Players
Classifier: Topic :: Multimedia :: Video
Classifier: Topic :: Software Development :: Libraries
Classifier: License :: OSI Approved :: GNU General Public License v3 or later (GPLv3+)
License-File: LICENSE
